regius/__init__.py
regius/app.py
regius/asyncio.py
regius/module.py
python_regius-0.2.0.dist-info/METADATA
python_regius-0.2.0.dist-info/WHEEL
python_regius-0.2.0.dist-info/entry_points.txt
python_regius-0.2.0.dist-info/RECORD
